.gitignore
CHANGES.rst
README.rst
bootstrap.py
buildout.cfg
setup.py
src/repoze/__init__.py
src/repoze.who.plugins.metadata_cache.egg-info/PKG-INFO
src/repoze.who.plugins.metadata_cache.egg-info/SOURCES.txt
src/repoze.who.plugins.metadata_cache.egg-info/dependency_links.txt
src/repoze.who.plugins.metadata_cache.egg-info/namespace_packages.txt
src/repoze.who.plugins.metadata_cache.egg-info/not-zip-safe
src/repoze.who.plugins.metadata_cache.egg-info/requires.txt
src/repoze.who.plugins.metadata_cache.egg-info/top_level.txt
src/repoze/who/__init__.py
src/repoze/who/plugins/__init__.py
src/repoze/who/plugins/metadata_cache/__init__.py
src/repoze/who/plugins/metadata_cache/base.py
src/repoze/who/plugins/metadata_cache/memory.py
src/repoze/who/plugins/metadata_cache/tests.py