Metadata-Version: 1.1
Name: repoze.who.plugins.metadata-cache
Version: 0.1
Summary: Metadata caching plugin for repoze.who
Home-page: http://github.com/davidjb/repoze.who.plugins.metadata_cache/
Author: David Beitey
Author-email: david@davidjb.com
License: BSD
Keywords: server web wsgi repoze repoze.who metadata
Platform: UNKNOWN
Classifier: Development Status :: 2 - Pre-Alpha
Classifier: Intended Audience :: Developers
Classifier: License :: OSI Approved :: BSD License
Classifier: Natural Language :: English
Classifier: Operating System :: OS Independent
Classifier: Programming Language :: Python
Classifier: Topic :: Internet :: WWW/HTTP :: WSGI :: Middleware
Classifier: Topic :: System :: Systems Administration :: Authentication/Directory
